python_dbus_system_api/__init__.py
python_dbus_system_api/interfaces/__init__.py
python_dbus_system_api/interfaces/volume.py
python_dbus_system_api/main.py
python_dbus_system_api-0.1.1.dist-info/entry_points.txt
python_dbus_system_api-0.1.1.dist-info/WHEEL
python_dbus_system_api-0.1.1.dist-info/METADATA
python_dbus_system_api-0.1.1.dist-info/RECORD
